atlas/__init__.py
atlas/comparer.py
atlas/creator.py
atlas/guarantor.py
atlas/locator.py
django_rest_atlas-0.0.0.dist-info/LICENSE
django_rest_atlas-0.0.0.dist-info/METADATA
django_rest_atlas-0.0.0.dist-info/WHEEL
django_rest_atlas-0.0.0.dist-info/top_level.txt
django_rest_atlas-0.0.0.dist-info/RECORD
