Metadata-Version: 2.1
Name: django-rest-atlas
Version: 0.0.0
Summary: Wrapper around Django rest framework for better routing experience
Home-page: https://github.com/Arnoldosmium/django-rest-atlas
Author: Arnold Lin
License: UNKNOWN
Keywords: django rest djangorestframework api
Platform: UNKNOWN
Classifier: Development Status :: 4 - Beta
Classifier: Framework :: Django
Classifier: Framework :: Django :: 2.0
Classifier: Framework :: Django :: 2.1
Classifier: Intended Audience :: Developers
Classifier: Topic :: Software Development :: Libraries
Classifier: License :: OSI Approved :: MIT License
Classifier: Programming Language :: Python :: 3
Classifier: Programming Language :: Python :: 3.4
Classifier: Programming Language :: Python :: 3.5
Classifier: Programming Language :: Python :: 3.6
Requires-Dist: Django (>=2.0)
Requires-Dist: djangorestframework (>=3.8.2)
Requires-Dist: django-filter (>=1.1.0)
Provides-Extra: test
Requires-Dist: pytest; extra == 'test'
